flowmark/__init__.py
flowmark/cli.py
flowmark/py.typed
flowmark/reformat_api.py
flowmark/formats/flowmark_markdown.py
flowmark/formats/frontmatter.py
flowmark/linewrapping/atomic_patterns.py
flowmark/linewrapping/block_heuristics.py
flowmark/linewrapping/line_wrappers.py
flowmark/linewrapping/markdown_filling.py
flowmark/linewrapping/protocols.py
flowmark/linewrapping/sentence_split_regex.py
flowmark/linewrapping/tag_handling.py
flowmark/linewrapping/text_filling.py
flowmark/linewrapping/text_wrapping.py
flowmark/transforms/doc_cleanups.py
flowmark/transforms/doc_transforms.py
flowmark/typography/ellipses.py
flowmark/typography/smartquotes.py
flowmark-0.6.1.dist-info/METADATA
flowmark-0.6.1.dist-info/WHEEL
flowmark-0.6.1.dist-info/entry_points.txt
flowmark-0.6.1.dist-info/licenses/LICENSE
flowmark-0.6.1.dist-info/RECORD
