Metadata-Version: 2.4
Name: flowmark
Version: 0.6.1
Summary: Better auto-formatting for Markdown and plaintext
Project-URL: Repository, https://github.com/jlevy/flowmark
Author-email: Joshua Levy <joshua@cal.berkeley.edu>
License-Expression: MIT
License-File: LICENSE
Classifier: Development Status :: 4 - Beta
Classifier: Intended Audience :: Developers
Classifier: Operating System :: OS Independent
Classifier: Programming Language :: Python
Classifier: Programming Language :: Python :: 3
Classifier: Programming Language :: Python :: 3.10
Classifier: Programming Language :: Python :: 3.11
Classifier: Programming Language :: Python :: 3.12
Classifier: Programming Language :: Python :: 3.13
Classifier: Programming Language :: Python :: 3.14
Classifier: Typing :: Typed
Requires-Python: <4.0,>=3.10
Requires-Dist: marko>=2.2.0
Requires-Dist: regex>=2024.11.6
Requires-Dist: strif>=3.0.1
Requires-Dist: typing-extensions>=4.12.2
